yolonnx-0.2.0.dist-info/METADATA
yolonnx-0.2.0.dist-info/WHEEL
yolonnx-0.2.0.dist-info/licenses/LICENSE
yolonnx/__init__.py
yolonnx/model.py
yolonnx/protocols.py
yolonnx/services/__init__.py
yolonnx/services/classifier.py
yolonnx/services/detector.py
yolonnx/to_tensor_strategies.py
yolonnx/utils.py
yolonnx-0.2.0.dist-info/RECORD
