Metadata-Version: 2.1
Name: yolonnx
Version: 0.2.0
Summary: This package lets you run your YOLOv8 detection and classification models using ONNXRuntime.
Keywords: ONNX,YOLOv8,onnxruntime,vision
Home-page: https://www.cs.aau.dk/
Author-Email: Kasper Fromm Pedersen <kasperf@cs.aau.dk>
License: MIT
Project-URL: Homepage, https://www.cs.aau.dk/
Project-URL: Repository, https://github.com/fromm1990/yolonnx
Requires-Python: <3.13,>=3.10
Requires-Dist: numpy==1.26.*
Requires-Dist: aau-label==0.*
